odoo/addons/website_snippet_big_button/README.rst
odoo/addons/website_snippet_big_button/__init__.py
odoo/addons/website_snippet_big_button/__manifest__.py
odoo/addons/website_snippet_big_button/i18n/ca.po
odoo/addons/website_snippet_big_button/i18n/es.po
odoo/addons/website_snippet_big_button/i18n/fr.po
odoo/addons/website_snippet_big_button/i18n/hr.po
odoo/addons/website_snippet_big_button/i18n/it.po
odoo/addons/website_snippet_big_button/i18n/pt_BR.po
odoo/addons/website_snippet_big_button/i18n/sl.po
odoo/addons/website_snippet_big_button/i18n/website_snippet_big_button.pot
odoo/addons/website_snippet_big_button/readme/CONTRIBUTORS.rst
odoo/addons/website_snippet_big_button/readme/DESCRIPTION.rst
odoo/addons/website_snippet_big_button/readme/USAGE.rst
odoo/addons/website_snippet_big_button/static/description/icon.png
odoo/addons/website_snippet_big_button/static/description/icon.svg
odoo/addons/website_snippet_big_button/static/description/index.html
odoo/addons/website_snippet_big_button/static/src/scss/website_snippet_big_button.scss
odoo/addons/website_snippet_big_button/templates/assets.xml
odoo/addons/website_snippet_big_button/templates/snippets.xml
odoo13_addon_website_snippet_big_button-13.0.1.0.1.dev7.dist-info/METADATA
odoo13_addon_website_snippet_big_button-13.0.1.0.1.dev7.dist-info/WHEEL
odoo13_addon_website_snippet_big_button-13.0.1.0.1.dev7.dist-info/top_level.txt
odoo13_addon_website_snippet_big_button-13.0.1.0.1.dev7.dist-info/RECORD
